{
    "Description": "",
    "ID": "a696deac0bfad29289ba8993840c",
    "Name": "portalEditor",
    "Permissions": {
        "AllCollections": {
            "Level": 0
        },
        "AllServices": {
            "Level": 0
        },
        "CodeServices": [],
        "Collections": [],
        "Deployments": {
            "Level": 0
        },
        "DevicesList": {
            "Level": 0
        },
        "EdgesList": {
            "Level": 0
        },
        "MsgHistory": {
            "Level": 0
        },
        "Portals": [
            {
                "Level": 5,
                "Name": "Two Factor Login",
                "SystemKey": "80ddb8b00bba80be9a94fbcdff41"
            }
        ],
        "Push": {
            "Level": 0
        },
        "Timers": {
            "Level": 0
        },
        "Topics": [],
        "Triggers": {
            "Level": 0
        },
        "UsersList": {
            "Level": 0
        }
    }
}